cjolowicz_scripts/__init__.py
cjolowicz_scripts/__main__.py
cjolowicz_scripts/compare_tools.py
cjolowicz_scripts/dependabot_rebase_all.py
cjolowicz_scripts/mbox2maildir.py
cjolowicz_scripts/py.typed
cjolowicz_scripts/pypi_dependents.py
cjolowicz_scripts/python_stdlib.py
cjolowicz_scripts/stardate.py
cjolowicz_scripts/yaml2json.py
cjolowicz_scripts-2022.1.9.dist-info/entry_points.txt
cjolowicz_scripts-2022.1.9.dist-info/LICENSE.rst
cjolowicz_scripts-2022.1.9.dist-info/WHEEL
cjolowicz_scripts-2022.1.9.dist-info/METADATA
cjolowicz_scripts-2022.1.9.dist-info/RECORD
