Metadata-Version: 2.1
Name: cjolowicz-scripts
Version: 2022.1.9
Summary: Miscellaneous Python scripts
Home-page: https://github.com/cjolowicz/python-scripts
License: MIT
Author: Claudio Jolowicz
Author-email: mail@claudiojolowicz.com
Requires-Python: >=3.10
Classifier: Development Status :: 4 - Beta
Classifier: License :: OSI Approved :: MIT License
Classifier: Programming Language :: Python :: 3
Classifier: Programming Language :: Python :: 3.10
Requires-Dist: PyYAML (>=6.0)
Requires-Dist: Pygments (>=2.10.0)
Requires-Dist: click (>=8.0.1)
Requires-Dist: github3.py (>=3.0.0)
Requires-Dist: httpx (>=0.21.1)
Requires-Dist: matplotlib (>=3.5.0)
Requires-Dist: platformdirs (>=2.4.0)
Requires-Dist: rich (>=10.15.2)
Project-URL: Changelog, https://github.com/cjolowicz/python-scripts/releases
Project-URL: Documentation, https://cjolowicz-scripts.readthedocs.io
Project-URL: Repository, https://github.com/cjolowicz/python-scripts
